quick_encrypt/quick_aes.py
quick_encrypt-0.2.dist-info/METADATA
quick_encrypt-0.2.dist-info/WHEEL
quick_encrypt-0.2.dist-info/top_level.txt
quick_encrypt-0.2.dist-info/RECORD
